{
    "duration": 0.08163265138864517,
    "lossless": 1.0,
    "codec": "pcm_f32le",
    "bitrate": 1411200.0,
    "samplerate": 44100.0,
    "channels": 1.0,
    "audio_md5": "ccadc469d95b890da6992f82d5e100a8",
    "loudness": -15.535762786865234,
    "dynamic_range": 0.0,
    "temporal_centroid": 0.6106383204460144,
    "log_attack_time": -1.263684868812561,
    "filesize": 14458,
    "single_event": false,
    "tonality": "D major",
    "tonality_confidence": 0.5363513827323914,
    "loop": false,
    "tempo": 0,
    "tempo_confidence": 0.0,
    "note_midi": 38,
    "note_name": "D2",
    "note_frequency": 73.42912292480469,
    "note_confidence": 0.8945459723472595,
    "hardness": 77.88990726027083,
    "depth": 42.01290002956563,
    "brightness": 61.28973170417987,
    "roughness": 75.13385085837656,
    "warmth": 42.33536042232229,
    "sharpness": 52.34040731998208,
    "boominess": 23.73020273474812,
    "reverb": false,
    "name": "AKWF_oscchip_0070.wav",
    "SpectralCentroid": 0.7554541197567785,
    "SpectralSpread": 0.7459456259203422,
    "SpectralKurtosis": 0.45898093682360386,
    "ZeroCrossingRate": 0.568873868296057,
    "SpectralComplexity": 1.0,
    "OddToEvenHarmonicEnergyRatio": 0.1725164509536531,
    "Dissonance": 0.9714413728154807,
    "PitchSalience": 0.9111151122656147,
    "HNR": 0.0,
    "NormalizeMethod": "ess_yeojohnson",
    "dco_brightness": 0.40011652613844545,
    "dco_richness": 0.6179204674467857,
    "dco_flatness": 0.6179204674467857,
    "dco_oddenergy": 0.8212064539059072,
    "dco_zcr": 0.2016028048315253
}