{
    "duration": 0.08163265138864517,
    "lossless": 1.0,
    "codec": "pcm_f32le",
    "bitrate": 1411200.0,
    "samplerate": 44100.0,
    "channels": 1.0,
    "audio_md5": "e0e9771c2860fed48cd3f4d6c910116b",
    "loudness": -13.382829666137695,
    "dynamic_range": 0.0,
    "temporal_centroid": 0.5792584419250488,
    "log_attack_time": -1.388442873954773,
    "filesize": 14458,
    "single_event": false,
    "tonality": "G major",
    "tonality_confidence": 0.44853872060775757,
    "loop": false,
    "tempo": 0,
    "tempo_confidence": 0.0,
    "note_midi": 38,
    "note_name": "D2",
    "note_frequency": 73.46659851074219,
    "note_confidence": 0.972165048122406,
    "hardness": 26.51742916776179,
    "depth": 63.54519882718428,
    "brightness": 25.350641333084162,
    "roughness": 39.72640295626662,
    "warmth": 56.2302202491271,
    "sharpness": 0.8314906834240219,
    "boominess": 54.063820468580545,
    "reverb": false,
    "name": "AKWF_0253.wav",
    "SpectralCentroid": 0.04397652503070602,
    "SpectralSpread": 0.03998408490982908,
    "SpectralKurtosis": 0.8026329871462794,
    "ZeroCrossingRate": 0.23302718649526455,
    "SpectralComplexity": 0.13432835820895522,
    "OddToEvenHarmonicEnergyRatio": 0.7046168072615853,
    "Dissonance": 0.660408306935205,
    "PitchSalience": 0.11847808621909646,
    "HNR": 0.6862746229408327,
    "NormalizeMethod": "ess_yeojohnson",
    "dco_brightness": 0.11631482307905028,
    "dco_richness": 0.16949023398152702,
    "dco_flatness": 0.16949023398152702,
    "dco_oddenergy": 0.08158529173126572,
    "dco_zcr": 0.06197413883311543
}