{
    "duration": 0.08163265138864517,
    "lossless": 1.0,
    "codec": "pcm_f32le",
    "bitrate": 1411200.0,
    "samplerate": 44100.0,
    "channels": 1.0,
    "audio_md5": "7721a3f6603a418e40a0127602cce10c",
    "loudness": -12.81434440612793,
    "dynamic_range": 0.0,
    "temporal_centroid": 0.5735524892807007,
    "log_attack_time": -1.4018971920013428,
    "filesize": 14458,
    "single_event": false,
    "tonality": "D major",
    "tonality_confidence": 0.45710277557373047,
    "loop": false,
    "tempo": 0,
    "tempo_confidence": 0.0,
    "note_midi": 38,
    "note_name": "D2",
    "note_frequency": 73.4594497680664,
    "note_confidence": 0.9591851234436035,
    "hardness": 34.728267652278205,
    "depth": 62.99724326320655,
    "brightness": 36.27614245951007,
    "roughness": 43.55305137407644,
    "warmth": 64.8567621143288,
    "sharpness": 14.56136046614926,
    "boominess": 48.00178356112421,
    "reverb": false,
    "name": "AKWF_1979.wav",
    "SpectralCentroid": 0.09621810266891354,
    "SpectralSpread": 0.06216389473983942,
    "SpectralKurtosis": 0.7516458741813564,
    "ZeroCrossingRate": 0.23302718649526455,
    "SpectralComplexity": 0.7761194029850746,
    "OddToEvenHarmonicEnergyRatio": 0.7855165931323138,
    "Dissonance": 0.8748054785184683,
    "PitchSalience": 0.3612106790747781,
    "HNR": 0.0,
    "NormalizeMethod": "ess_yeojohnson",
    "dco_brightness": 0.12946882573892252,
    "dco_richness": 0.24306670550765064,
    "dco_flatness": 0.24306670550765064,
    "dco_oddenergy": 0.044768500418327584,
    "dco_zcr": 0.06197413883311543
}