{
    "duration": 0.08163265138864517,
    "lossless": 1.0,
    "codec": "pcm_f32le",
    "bitrate": 1411200.0,
    "samplerate": 44100.0,
    "channels": 1.0,
    "audio_md5": "2921d2d18b45291af78cd9f039c2507f",
    "loudness": -15.94245719909668,
    "dynamic_range": 0.0,
    "temporal_centroid": 0.5878377556800842,
    "log_attack_time": -1.2965234518051147,
    "filesize": 14458,
    "single_event": false,
    "tonality": "D major",
    "tonality_confidence": 0.8286200761795044,
    "loop": false,
    "tempo": 0,
    "tempo_confidence": 0.0,
    "note_midi": 38,
    "note_name": "D2",
    "note_frequency": 73.44573974609375,
    "note_confidence": 0.9675069451332092,
    "hardness": 29.34360918556331,
    "depth": 62.720633915051216,
    "brightness": 26.228914725661962,
    "roughness": 46.852829654315094,
    "warmth": 66.26236691255187,
    "sharpness": 0.0,
    "boominess": 53.32876802086302,
    "reverb": false,
    "name": "AKWF_1185.wav",
    "SpectralCentroid": 0.0481301936428963,
    "SpectralSpread": 0.02586727214707306,
    "SpectralKurtosis": 0.8089877823104296,
    "ZeroCrossingRate": 0.23302718649526455,
    "SpectralComplexity": 0.2835820895522388,
    "OddToEvenHarmonicEnergyRatio": 0.27217278370303094,
    "Dissonance": 0.6496723549308825,
    "PitchSalience": 0.575476662143583,
    "HNR": 0.0,
    "NormalizeMethod": "ess_yeojohnson",
    "dco_brightness": 0.1301551303766631,
    "dco_richness": 0.25621207213972397,
    "dco_flatness": 0.25621207213972397,
    "dco_oddenergy": 0.38638434240881714,
    "dco_zcr": 0.06197413883311543
}