{
    "duration": 0.08163265138864517,
    "lossless": 1.0,
    "codec": "pcm_f32le",
    "bitrate": 1411200.0,
    "samplerate": 44100.0,
    "channels": 1.0,
    "audio_md5": "8374f5e745b7f664b14605bd9af48422",
    "loudness": -14.552956581115723,
    "dynamic_range": 0.0,
    "temporal_centroid": 0.5835564732551575,
    "log_attack_time": -1.3061813116073608,
    "filesize": 14458,
    "single_event": false,
    "tonality": "D major",
    "tonality_confidence": 0.9043893218040466,
    "loop": false,
    "tempo": 0,
    "tempo_confidence": 0.0,
    "note_midi": 38,
    "note_name": "D2",
    "note_frequency": 73.44242095947266,
    "note_confidence": 0.932995617389679,
    "hardness": 39.383051863306804,
    "depth": 60.08333039504876,
    "brightness": 35.318773031258786,
    "roughness": 52.92753165985597,
    "warmth": 72.02317171105416,
    "sharpness": 8.967179332758466,
    "boominess": 45.624141484473,
    "reverb": false,
    "name": "AKWF_piano_0023.wav",
    "SpectralCentroid": 0.13049290371954966,
    "SpectralSpread": 0.016520723448356627,
    "SpectralKurtosis": 0.7866117273912089,
    "ZeroCrossingRate": 0.4252420127794052,
    "SpectralComplexity": 0.582089552238806,
    "OddToEvenHarmonicEnergyRatio": 0.08920250236801058,
    "Dissonance": 0.9993952839882345,
    "PitchSalience": 0.45988341964527657,
    "HNR": 0.5922119376560507,
    "NormalizeMethod": "ess_yeojohnson",
    "dco_brightness": 0.2034617005439894,
    "dco_richness": 0.31333690381622503,
    "dco_flatness": 0.31333690381622503,
    "dco_oddenergy": 0.8402578822902306,
    "dco_zcr": 0.14487511069267625
}