{
    "duration": 0.08163265138864517,
    "lossless": 1.0,
    "codec": "pcm_f32le",
    "bitrate": 1411200.0,
    "samplerate": 44100.0,
    "channels": 1.0,
    "audio_md5": "30e0d889da6b1bc0d86ef5998a4e18de",
    "loudness": -11.261191368103027,
    "dynamic_range": 0.0,
    "temporal_centroid": 0.5713208913803101,
    "log_attack_time": -1.5011115074157715,
    "filesize": 14458,
    "single_event": false,
    "tonality": "D major",
    "tonality_confidence": 0.8128957152366638,
    "loop": false,
    "tempo": 0,
    "tempo_confidence": 0.0,
    "note_midi": 38,
    "note_name": "D2",
    "note_frequency": 73.42847442626953,
    "note_confidence": 0.9957326054573059,
    "hardness": 64.72494366219658,
    "depth": 61.25833225842368,
    "brightness": 57.89394396276383,
    "roughness": 60.79264831245553,
    "warmth": 46.161627666635425,
    "sharpness": 49.69055719857131,
    "boominess": 36.28613382147512,
    "reverb": false,
    "name": "AKWF_blended_0014.wav",
    "SpectralCentroid": 0.7838013151966633,
    "SpectralSpread": 0.8750154076442487,
    "SpectralKurtosis": 0.4359076732961258,
    "ZeroCrossingRate": 0.23302718649526455,
    "SpectralComplexity": 1.0,
    "OddToEvenHarmonicEnergyRatio": 0.6451141521452561,
    "Dissonance": 0.9807521468111314,
    "PitchSalience": 0.31169645074513846,
    "HNR": 0.0,
    "NormalizeMethod": "ess_yeojohnson",
    "dco_brightness": 0.2003741641247612,
    "dco_richness": 0.5569698813430544,
    "dco_flatness": 0.5569698813430544,
    "dco_oddenergy": 0.14125339273005855,
    "dco_zcr": 0.06197413883311543
}