{
    "duration": 0.08163265138864517,
    "lossless": 1.0,
    "codec": "pcm_f32le",
    "bitrate": 1411200.0,
    "samplerate": 44100.0,
    "channels": 1.0,
    "audio_md5": "358e7d11c9484c0017ebece5718f7fc3",
    "loudness": -10.384092330932617,
    "dynamic_range": 0.0,
    "temporal_centroid": 0.5686832666397095,
    "log_attack_time": -1.4620239734649658,
    "filesize": 14458,
    "single_event": false,
    "tonality": "D major",
    "tonality_confidence": 0.6583313345909119,
    "loop": false,
    "tempo": 0,
    "tempo_confidence": 0.0,
    "note_midi": 50,
    "note_name": "D3",
    "note_frequency": 147.16685485839844,
    "note_confidence": 0.9211013317108154,
    "hardness": 51.16376423992156,
    "depth": 53.84461102933484,
    "brightness": 47.29126609357708,
    "roughness": 57.71614123781836,
    "warmth": 66.34972862273342,
    "sharpness": 28.455006821420714,
    "boominess": 36.48726935365456,
    "reverb": false,
    "name": "AKWF_0451.wav",
    "SpectralCentroid": 0.2550229173267738,
    "SpectralSpread": 0.091484260317916,
    "SpectralKurtosis": 0.6570206422305238,
    "ZeroCrossingRate": 0.6763055176555212,
    "SpectralComplexity": 1.0,
    "OddToEvenHarmonicEnergyRatio": 0.016256210312937128,
    "Dissonance": 0.9709917926084463,
    "PitchSalience": 0.6466069726475138,
    "HNR": 0.8575827354847737,
    "NormalizeMethod": "ess_yeojohnson",
    "dco_brightness": 0.24757909162483605,
    "dco_richness": 0.40614156156885123,
    "dco_flatness": 0.40614156156885123,
    "dco_oddenergy": 0.9672834829222512,
    "dco_zcr": 0.24477676146998018
}