{
    "duration": 0.08163265138864517,
    "lossless": 1.0,
    "codec": "pcm_f32le",
    "bitrate": 1411200.0,
    "samplerate": 44100.0,
    "channels": 1.0,
    "audio_md5": "3353981f3c97e059b51e397e47d2f639",
    "loudness": -11.736852645874023,
    "dynamic_range": 0.0,
    "temporal_centroid": 0.5710741877555847,
    "log_attack_time": -1.4857745170593262,
    "filesize": 14458,
    "single_event": false,
    "tonality": "D major",
    "tonality_confidence": 0.7282650470733643,
    "loop": false,
    "tempo": 0,
    "tempo_confidence": 0.0,
    "note_midi": 38,
    "note_name": "D2",
    "note_frequency": 73.42897033691406,
    "note_confidence": 0.9908473491668701,
    "hardness": 56.44320940984028,
    "depth": 61.712182549549084,
    "brightness": 50.487673914981244,
    "roughness": 56.451064838079084,
    "warmth": 52.72956405451181,
    "sharpness": 40.296460335399075,
    "boominess": 39.67027122682337,
    "reverb": false,
    "name": "AKWF_0460.wav",
    "SpectralCentroid": 0.6166106276925093,
    "SpectralSpread": 0.7778545477079638,
    "SpectralKurtosis": 0.5030580992475523,
    "ZeroCrossingRate": 0.23302718649526455,
    "SpectralComplexity": 1.0,
    "OddToEvenHarmonicEnergyRatio": 0.7010289776533735,
    "Dissonance": 0.9775361604274893,
    "PitchSalience": 0.4065635063488058,
    "HNR": 0.0,
    "NormalizeMethod": "ess_yeojohnson",
    "dco_brightness": 0.15972294521950478,
    "dco_richness": 0.4748319659641407,
    "dco_flatness": 0.4748319659641407,
    "dco_oddenergy": 0.0918279963254589,
    "dco_zcr": 0.10810914741925219
}