{
    "duration": 0.08163265138864517,
    "lossless": 1.0,
    "codec": "pcm_f32le",
    "bitrate": 1411200.0,
    "samplerate": 44100.0,
    "channels": 1.0,
    "audio_md5": "312b3c70aa01e6a5569402027af63c73",
    "loudness": -16.479557037353516,
    "dynamic_range": 0.0,
    "temporal_centroid": 0.5932007431983948,
    "log_attack_time": -1.266586184501648,
    "filesize": 14458,
    "single_event": false,
    "tonality": "D major",
    "tonality_confidence": 0.7966850399971008,
    "loop": false,
    "tempo": 0,
    "tempo_confidence": 0.0,
    "note_midi": 38,
    "note_name": "D2",
    "note_frequency": 73.42839813232422,
    "note_confidence": 0.9319241046905518,
    "hardness": 67.14851922959252,
    "depth": 58.42156434587534,
    "brightness": 56.31490353444332,
    "roughness": 65.50838104054202,
    "warmth": 53.009973379835195,
    "sharpness": 49.08981621388977,
    "boominess": 36.92830524165752,
    "reverb": false,
    "name": "AKWF_oscchip_0007.wav",
    "SpectralCentroid": 0.6774400190772806,
    "SpectralSpread": 0.6692248881070159,
    "SpectralKurtosis": 0.4804982646690931,
    "ZeroCrossingRate": 0.568873868296057,
    "SpectralComplexity": 1.0,
    "OddToEvenHarmonicEnergyRatio": 0.36408120454439785,
    "Dissonance": 0.9828300330081147,
    "PitchSalience": 0.3554827299778975,
    "HNR": 0.0,
    "NormalizeMethod": "ess_yeojohnson",
    "dco_brightness": 0.2365965948278638,
    "dco_richness": 0.5420745944549366,
    "dco_flatness": 0.5420745944549366,
    "dco_oddenergy": 0.43396816493619905,
    "dco_zcr": 0.2016028048315253
}