{
    "duration": 0.08163265138864517,
    "lossless": 1.0,
    "codec": "pcm_f32le",
    "bitrate": 1411200.0,
    "samplerate": 44100.0,
    "channels": 1.0,
    "audio_md5": "d05b11b7015fd8707d96df71e2030002",
    "loudness": -14.978897094726562,
    "dynamic_range": 0.0,
    "temporal_centroid": 0.5863884687423706,
    "log_attack_time": -1.274851679801941,
    "filesize": 14458,
    "single_event": false,
    "tonality": "D major",
    "tonality_confidence": 0.8238175511360168,
    "loop": false,
    "tempo": 0,
    "tempo_confidence": 0.0,
    "note_midi": 38,
    "note_name": "D2",
    "note_frequency": 73.43352508544922,
    "note_confidence": 0.9315159320831299,
    "hardness": 53.982741096540394,
    "depth": 57.23593308691876,
    "brightness": 48.798364233244115,
    "roughness": 57.67022520827984,
    "warmth": 61.80966867039935,
    "sharpness": 33.1809079435886,
    "boominess": 36.64775002208501,
    "reverb": false,
    "name": "AKWF_1623.wav",
    "SpectralCentroid": 0.2840331213374959,
    "SpectralSpread": 0.13804702303564656,
    "SpectralKurtosis": 0.6297374260591306,
    "ZeroCrossingRate": 0.568873868296057,
    "SpectralComplexity": 0.9850746268656716,
    "OddToEvenHarmonicEnergyRatio": 0.38336465522965174,
    "Dissonance": 0.9770035785534196,
    "PitchSalience": 0.6499289748870247,
    "HNR": 0.0,
    "NormalizeMethod": "ess_yeojohnson",
    "dco_brightness": 0.22354133047529023,
    "dco_richness": 0.4155696685071042,
    "dco_flatness": 0.4155696685071042,
    "dco_oddenergy": 0.37745083581346084,
    "dco_zcr": 0.2016028048315253
}