{
    "duration": 0.08163265138864517,
    "lossless": 1.0,
    "codec": "pcm_f32le",
    "bitrate": 1411200.0,
    "samplerate": 44100.0,
    "channels": 1.0,
    "audio_md5": "ace72aac8b5b9c767d50f260d7ba53e3",
    "loudness": -13.292280197143555,
    "dynamic_range": 0.0,
    "temporal_centroid": 0.5877935290336609,
    "log_attack_time": -1.3067797422409058,
    "filesize": 14458,
    "single_event": false,
    "tonality": "D minor",
    "tonality_confidence": 0.6283900141716003,
    "loop": false,
    "tempo": 0,
    "tempo_confidence": 0.0,
    "note_midi": 38,
    "note_name": "D2",
    "note_frequency": 73.42839813232422,
    "note_confidence": 0.9499595165252686,
    "hardness": 73.25433272021638,
    "depth": 59.15754753095895,
    "brightness": 60.64387395332538,
    "roughness": 64.86438303003247,
    "warmth": 43.43268390351005,
    "sharpness": 51.04593671141053,
    "boominess": 34.43372731488947,
    "reverb": false,
    "name": "AKWF_1517.wav",
    "SpectralCentroid": 0.8087128011404106,
    "SpectralSpread": 0.885222428580126,
    "SpectralKurtosis": 0.42159198744429255,
    "ZeroCrossingRate": 0.23302718649526455,
    "SpectralComplexity": 1.0,
    "OddToEvenHarmonicEnergyRatio": 0.13029088661200075,
    "Dissonance": 0.9732177397756242,
    "PitchSalience": 0.3486382706271462,
    "HNR": 0.32689446191587684,
    "NormalizeMethod": "ess_yeojohnson",
    "dco_brightness": 0.2666995263415108,
    "dco_richness": 0.6063812573454755,
    "dco_flatness": 0.6063812573454755,
    "dco_oddenergy": 0.3047459623619597,
    "dco_zcr": 0.10810914741925219
}