{
    "duration": 0.08163265138864517,
    "lossless": 1.0,
    "codec": "pcm_f32le",
    "bitrate": 1411200.0,
    "samplerate": 44100.0,
    "channels": 1.0,
    "audio_md5": "07f03becea7e5f341e9d236744088d2e",
    "loudness": -13.870695114135742,
    "dynamic_range": 0.0,
    "temporal_centroid": 0.5837144255638123,
    "log_attack_time": -1.3043912649154663,
    "filesize": 14458,
    "single_event": false,
    "tonality": "D minor",
    "tonality_confidence": 0.7310434579849243,
    "loop": false,
    "tempo": 0,
    "tempo_confidence": 0.0,
    "note_midi": 38,
    "note_name": "D2",
    "note_frequency": 73.45906829833984,
    "note_confidence": 0.973253071308136,
    "hardness": 25.40723613948977,
    "depth": 54.65403806530641,
    "brightness": 25.470767244174695,
    "roughness": 45.39700952869366,
    "warmth": 64.24386216942472,
    "sharpness": 0.0,
    "boominess": 56.052267719782165,
    "reverb": false,
    "name": "AKWF_oboe_0001.wav",
    "SpectralCentroid": 0.03983359072333972,
    "SpectralSpread": 0.016342921376247207,
    "SpectralKurtosis": 0.8447371586492819,
    "ZeroCrossingRate": 0.23302718649526455,
    "SpectralComplexity": 0.3283582089552239,
    "OddToEvenHarmonicEnergyRatio": 0.6196410247949583,
    "Dissonance": 0.6802678780339371,
    "PitchSalience": 0.21435954121108736,
    "HNR": 0.8430918706342126,
    "NormalizeMethod": "ess_yeojohnson",
    "dco_brightness": 0.12254053097701,
    "dco_richness": 0.1827147853929934,
    "dco_flatness": 0.1827147853929934,
    "dco_oddenergy": 0.13368952576014936,
    "dco_zcr": 0.06197413883311543
}