{
    "duration": 0.08163265138864517,
    "lossless": 1.0,
    "codec": "pcm_f32le",
    "bitrate": 1411200.0,
    "samplerate": 44100.0,
    "channels": 1.0,
    "audio_md5": "cf82f713b903865a9dc5d70412d220ab",
    "loudness": -14.416019439697266,
    "dynamic_range": 0.0,
    "temporal_centroid": 0.5835229158401489,
    "log_attack_time": -1.2649518251419067,
    "filesize": 14458,
    "single_event": false,
    "tonality": "D major",
    "tonality_confidence": 0.7963228225708008,
    "loop": false,
    "tempo": 0,
    "tempo_confidence": 0.0,
    "note_midi": 38,
    "note_name": "D2",
    "note_frequency": 73.44066619873047,
    "note_confidence": 0.9439656138420105,
    "hardness": 32.126719211607394,
    "depth": 55.56236000516342,
    "brightness": 27.98193166167246,
    "roughness": 49.11889555027834,
    "warmth": 75.587396261988,
    "sharpness": 4.299872155572629,
    "boominess": 46.24418758734561,
    "reverb": false,
    "name": "AKWF_0479.wav",
    "SpectralCentroid": 0.08970674909717644,
    "SpectralSpread": 0.0031970150769462455,
    "SpectralKurtosis": 0.9002438714950889,
    "ZeroCrossingRate": 0.568873868296057,
    "SpectralComplexity": 0.373134328358209,
    "OddToEvenHarmonicEnergyRatio": 0.39089344596163655,
    "Dissonance": 0.8807674488759328,
    "PitchSalience": 0.437847815553118,
    "HNR": 0.7421692810263459,
    "NormalizeMethod": "ess_yeojohnson",
    "dco_brightness": 0.2220615925310552,
    "dco_richness": 0.23462605264111322,
    "dco_flatness": 0.23462605264111322,
    "dco_oddenergy": 0.3517123350604269,
    "dco_zcr": 0.2016028048315253
}