{
    "duration": 0.08163265138864517,
    "lossless": 1.0,
    "codec": "pcm_f32le",
    "bitrate": 1411200.0,
    "samplerate": 44100.0,
    "channels": 1.0,
    "audio_md5": "cc0d9566eed8dc36088e7a1defe22a8e",
    "loudness": -17.200605392456055,
    "dynamic_range": 0.0,
    "temporal_centroid": 0.6128199696540833,
    "log_attack_time": -1.2574049234390259,
    "filesize": 14458,
    "single_event": false,
    "tonality": "D major",
    "tonality_confidence": 0.7882038950920105,
    "loop": false,
    "tempo": 0,
    "tempo_confidence": 0.0,
    "note_midi": 38,
    "note_name": "D2",
    "note_frequency": 73.45368957519531,
    "note_confidence": 0.9417081475257874,
    "hardness": 34.884108881440426,
    "depth": 62.22393018264809,
    "brightness": 30.18931147581497,
    "roughness": 47.50089571735864,
    "warmth": 69.08718268973837,
    "sharpness": 4.0542127487141,
    "boominess": 51.56104282213491,
    "reverb": false,
    "name": "AKWF_ebass_0035.wav",
    "SpectralCentroid": 0.07188873226731486,
    "SpectralSpread": 0.04731489430131303,
    "SpectralKurtosis": 0.7761586806789126,
    "ZeroCrossingRate": 0.23302718649526455,
    "SpectralComplexity": 0.34328358208955223,
    "OddToEvenHarmonicEnergyRatio": 0.25602069384031284,
    "Dissonance": 0.6332069539350959,
    "PitchSalience": 0.6148430655888335,
    "HNR": 0.0,
    "NormalizeMethod": "ess_yeojohnson",
    "dco_brightness": 0.16146984922785315,
    "dco_richness": 0.25726961245737046,
    "dco_flatness": 0.25726961245737046,
    "dco_oddenergy": 0.49464870830467955,
    "dco_zcr": 0.06197413883311543
}