{
    "duration": 0.08163265138864517,
    "lossless": 1.0,
    "codec": "pcm_f32le",
    "bitrate": 1411200.0,
    "samplerate": 44100.0,
    "channels": 1.0,
    "audio_md5": "762658fc7d01757003b008d008ee3bf9",
    "loudness": -14.470478057861328,
    "dynamic_range": 0.0,
    "temporal_centroid": 0.5859360098838806,
    "log_attack_time": -1.3093820810317993,
    "filesize": 14458,
    "single_event": false,
    "tonality": "D minor",
    "tonality_confidence": 0.6647942662239075,
    "loop": false,
    "tempo": 0,
    "tempo_confidence": 0.0,
    "note_midi": 50,
    "note_name": "D3",
    "note_frequency": 145.76890563964844,
    "note_confidence": 0.8626856803894043,
    "hardness": 51.1119712471268,
    "depth": 49.391238471835806,
    "brightness": 43.43130600709231,
    "roughness": 56.080662719504595,
    "warmth": 68.36577800448043,
    "sharpness": 30.619445245595386,
    "boominess": 40.9718875515309,
    "reverb": false,
    "name": "AKWF_1687.wav",
    "SpectralCentroid": 0.28355596870225586,
    "SpectralSpread": 0.13376633323191725,
    "SpectralKurtosis": 0.6155413199583758,
    "ZeroCrossingRate": 0.568873868296057,
    "SpectralComplexity": 1.0,
    "OddToEvenHarmonicEnergyRatio": 0.03055795558601653,
    "Dissonance": 0.92011250008023,
    "PitchSalience": 0.4334055879603024,
    "HNR": 0.823567401387404,
    "NormalizeMethod": "ess_yeojohnson",
    "dco_brightness": 0.21366811276105055,
    "dco_richness": 0.37384781339479367,
    "dco_flatness": 0.37384781339479367,
    "dco_oddenergy": 0.9657888405177494,
    "dco_zcr": 0.2016028048315253
}