{
    "duration": 0.08163265138864517,
    "lossless": 1.0,
    "codec": "pcm_f32le",
    "bitrate": 1411200.0,
    "samplerate": 44100.0,
    "channels": 1.0,
    "audio_md5": "300ef737ed04d4865062be8938d43f9c",
    "loudness": -16.5001220703125,
    "dynamic_range": 0.0,
    "temporal_centroid": 0.5873702764511108,
    "log_attack_time": -1.2658590078353882,
    "filesize": 14458,
    "single_event": false,
    "tonality": "D major",
    "tonality_confidence": 0.35806572437286377,
    "loop": false,
    "tempo": 0,
    "tempo_confidence": 0.0,
    "note_midi": 38,
    "note_name": "D2",
    "note_frequency": 73.43108367919922,
    "note_confidence": 0.9727904796600342,
    "hardness": 43.000818363342546,
    "depth": 51.27555545685912,
    "brightness": 42.433389534881826,
    "roughness": 54.831071204247806,
    "warmth": 68.4570615665875,
    "sharpness": 22.41449808028958,
    "boominess": 38.175310350292534,
    "reverb": false
}