{
    "duration": 0.08163265138864517,
    "lossless": 1.0,
    "codec": "pcm_f32le",
    "bitrate": 1411200.0,
    "samplerate": 44100.0,
    "channels": 1.0,
    "audio_md5": "880fd182a73fef2f18d8fd0c5713ed9a",
    "loudness": -18.76592445373535,
    "dynamic_range": 0.0,
    "temporal_centroid": 0.6099613308906555,
    "log_attack_time": -1.1842927932739258,
    "filesize": 14458,
    "single_event": false,
    "tonality": "D major",
    "tonality_confidence": 0.7312285304069519,
    "loop": false,
    "tempo": 0,
    "tempo_confidence": 0.0,
    "note_midi": 38,
    "note_name": "D2",
    "note_frequency": 73.43128967285156,
    "note_confidence": 0.8651840686798096,
    "hardness": 63.67422063364944,
    "depth": 39.62037493326221,
    "brightness": 53.856873071837555,
    "roughness": 64.24689937295669,
    "warmth": 51.48958856958618,
    "sharpness": 43.23828838724094,
    "boominess": 22.644343841572827,
    "reverb": false
}