{
    "duration": 0.08163265138864517,
    "lossless": 1.0,
    "codec": "pcm_f32le",
    "bitrate": 1411200.0,
    "samplerate": 44100.0,
    "channels": 1.0,
    "audio_md5": "b7d9da1d195846a63171b45c96d9417d",
    "loudness": -13.150627136230469,
    "dynamic_range": 0.0,
    "temporal_centroid": 0.5800980925559998,
    "log_attack_time": -1.3477734327316284,
    "filesize": 14458,
    "single_event": false,
    "tonality": "A minor",
    "tonality_confidence": 0.5152862668037415,
    "loop": false,
    "tempo": 0,
    "tempo_confidence": 0.0,
    "note_midi": 38,
    "note_name": "D2",
    "note_frequency": 73.447998046875,
    "note_confidence": 0.9473816752433777,
    "hardness": 34.81834616653984,
    "depth": 61.52970849793373,
    "brightness": 33.79436319002683,
    "roughness": 49.89216440515629,
    "warmth": 72.2026098150437,
    "sharpness": 8.966152804492786,
    "boominess": 46.69238616284312,
    "reverb": false
}