{
    "duration": 0.08163265138864517,
    "lossless": 1.0,
    "codec": "pcm_f32le",
    "bitrate": 1411200.0,
    "samplerate": 44100.0,
    "channels": 1.0,
    "audio_md5": "909d8cbe9d8f545332f723a0cf33aebf",
    "loudness": -11.324002265930176,
    "dynamic_range": 0.0,
    "temporal_centroid": 0.5642601251602173,
    "log_attack_time": -1.5396101474761963,
    "filesize": 14458,
    "single_event": false,
    "tonality": "C minor",
    "tonality_confidence": 0.35023489594459534,
    "loop": false,
    "tempo": 0,
    "tempo_confidence": 0.0,
    "note_midi": 38,
    "note_name": "D2",
    "note_frequency": 73.45511627197266,
    "note_confidence": 0.9754559993743896,
    "hardness": 30.002010456476498,
    "depth": 54.62905846346845,
    "brightness": 33.10758994545161,
    "roughness": 29.32485668499425,
    "warmth": 65.38027974695633,
    "sharpness": 6.514323335767802,
    "boominess": 51.56003624364806,
    "reverb": false
}