{
    "duration": 0.08163265138864517,
    "lossless": 1.0,
    "codec": "pcm_f32le",
    "bitrate": 1411200.0,
    "samplerate": 44100.0,
    "channels": 1.0,
    "audio_md5": "d7b273ca1597438754e7ac079626dd69",
    "loudness": -14.13440227508545,
    "dynamic_range": 0.0,
    "temporal_centroid": 0.5862131118774414,
    "log_attack_time": -1.2907146215438843,
    "filesize": 14458,
    "single_event": false,
    "tonality": "D minor",
    "tonality_confidence": 0.8504632711410522,
    "loop": false,
    "tempo": 0,
    "tempo_confidence": 0.0,
    "note_midi": 38,
    "note_name": "D2",
    "note_frequency": 73.44522857666016,
    "note_confidence": 0.9362931251525879,
    "hardness": 34.54163992790677,
    "depth": 60.30929887826946,
    "brightness": 29.197918053319288,
    "roughness": 50.29845972959175,
    "warmth": 67.67643030461024,
    "sharpness": 4.634453148531922,
    "boominess": 47.106349114298865,
    "reverb": false
}