{
    "duration": 0.08163265138864517,
    "lossless": 1.0,
    "codec": "pcm_f32le",
    "bitrate": 1411200.0,
    "samplerate": 44100.0,
    "channels": 1.0,
    "audio_md5": "647bcbaaaee357982add7a83021c0b76",
    "loudness": -15.677582740783691,
    "dynamic_range": 0.0,
    "temporal_centroid": 0.6107822060585022,
    "log_attack_time": -1.2649517059326172,
    "filesize": 14458,
    "single_event": false,
    "tonality": "A major",
    "tonality_confidence": 0.7286638021469116,
    "loop": false,
    "tempo": 0,
    "tempo_confidence": 0.0,
    "note_midi": 38,
    "note_name": "D2",
    "note_frequency": 73.42916107177734,
    "note_confidence": 0.9959806799888611,
    "hardness": 48.03247982074842,
    "depth": 52.996038556219204,
    "brightness": 43.8277922590669,
    "roughness": 52.080393540031864,
    "warmth": 67.07433826568789,
    "sharpness": 34.0241089480968,
    "boominess": 41.464136521351236,
    "reverb": false
}