{
    "duration": 0.08163265138864517,
    "lossless": 1.0,
    "codec": "pcm_f32le",
    "bitrate": 1411200.0,
    "samplerate": 44100.0,
    "channels": 1.0,
    "audio_md5": "97415887990218711e82a7b293c6ddef",
    "loudness": -10.921335220336914,
    "dynamic_range": 0.0,
    "temporal_centroid": 0.5768657922744751,
    "log_attack_time": -1.3758606910705566,
    "filesize": 14458,
    "single_event": false,
    "tonality": "D major",
    "tonality_confidence": 0.5816447138786316,
    "loop": false,
    "tempo": 0,
    "tempo_confidence": 0.0,
    "note_midi": 38,
    "note_name": "D2",
    "note_frequency": 73.43099212646484,
    "note_confidence": 0.9710996150970459,
    "hardness": 38.600487774279,
    "depth": 49.589910886397334,
    "brightness": 37.622557746853275,
    "roughness": 48.198954930432976,
    "warmth": 65.10631468037901,
    "sharpness": 14.298123171393819,
    "boominess": 38.18989274515957,
    "reverb": false
}