{
    "duration": 0.08163265138864517,
    "lossless": 1.0,
    "codec": "pcm_f32le",
    "bitrate": 1411200.0,
    "samplerate": 44100.0,
    "channels": 1.0,
    "audio_md5": "360ea8c94430ed29a26c221eba98ee31",
    "loudness": -15.548001289367676,
    "dynamic_range": 0.0,
    "temporal_centroid": 0.5687043070793152,
    "log_attack_time": -1.3935309648513794,
    "filesize": 14458,
    "single_event": false,
    "tonality": "D major",
    "tonality_confidence": 0.769598126411438,
    "loop": false,
    "tempo": 0,
    "tempo_confidence": 0.0,
    "note_midi": 38,
    "note_name": "D2",
    "note_frequency": 73.42839813232422,
    "note_confidence": 0.9235683083534241,
    "hardness": 79.10851975200484,
    "depth": 52.53762583408514,
    "brightness": 62.625078083921125,
    "roughness": 70.96067860792493,
    "warmth": 43.433618640121196,
    "sharpness": 52.36693185176476,
    "boominess": 27.962034325394548,
    "reverb": false
}