{
    "duration": 0.08163265138864517,
    "lossless": 1.0,
    "codec": "pcm_f32le",
    "bitrate": 1411200.0,
    "samplerate": 44100.0,
    "channels": 1.0,
    "audio_md5": "865f68931ae5722764e519930f8e7670",
    "loudness": -12.708063125610352,
    "dynamic_range": 0.0,
    "temporal_centroid": 0.5782030820846558,
    "log_attack_time": -1.3643157482147217,
    "filesize": 14458,
    "single_event": false,
    "tonality": "D minor",
    "tonality_confidence": 0.7093390226364136,
    "loop": false,
    "tempo": 0,
    "tempo_confidence": 0.0,
    "note_midi": 50,
    "note_name": "D3",
    "note_frequency": 146.39637756347656,
    "note_confidence": 0.9038776159286499,
    "hardness": 32.2851382415506,
    "depth": 59.362663259417545,
    "brightness": 33.40660112508097,
    "roughness": 45.59677986172904,
    "warmth": 65.11655574528424,
    "sharpness": 9.663480861710426,
    "boominess": 51.5016069781024,
    "reverb": false
}