{
    "duration": 0.08163265138864517,
    "lossless": 1.0,
    "codec": "pcm_f32le",
    "bitrate": 1411200.0,
    "samplerate": 44100.0,
    "channels": 1.0,
    "audio_md5": "18dfa0de0511281e1b34285468c7b768",
    "loudness": -14.339998245239258,
    "dynamic_range": 0.0,
    "temporal_centroid": 0.5827557444572449,
    "log_attack_time": -1.3393023014068604,
    "filesize": 14458,
    "single_event": false,
    "tonality": "D major",
    "tonality_confidence": 0.8189592361450195,
    "loop": false,
    "tempo": 0,
    "tempo_confidence": 0.0,
    "note_midi": 38,
    "note_name": "D2",
    "note_frequency": 73.43257141113281,
    "note_confidence": 0.9788380861282349,
    "hardness": 46.54785751815797,
    "depth": 60.902265642689784,
    "brightness": 46.16136254147111,
    "roughness": 55.61877356328374,
    "warmth": 62.74734997545012,
    "sharpness": 28.242956159512232,
    "boominess": 41.054270337753344,
    "reverb": false
}