{
    "duration": 0.08163265138864517,
    "lossless": 1.0,
    "codec": "pcm_f32le",
    "bitrate": 1411200.0,
    "samplerate": 44100.0,
    "channels": 1.0,
    "audio_md5": "4184d1df6cffc8a747fe37ec607ad2ba",
    "loudness": -14.807173728942871,
    "dynamic_range": 0.0,
    "temporal_centroid": 0.5854718685150146,
    "log_attack_time": -1.3255409002304077,
    "filesize": 14458,
    "single_event": false,
    "tonality": "D major",
    "tonality_confidence": 0.7224404215812683,
    "loop": false,
    "tempo": 0,
    "tempo_confidence": 0.0,
    "note_midi": 38,
    "note_name": "D2",
    "note_frequency": 73.43989562988281,
    "note_confidence": 0.9924557209014893,
    "hardness": 28.64532530686408,
    "depth": 63.60894936664715,
    "brightness": 31.725735888732586,
    "roughness": 46.2630008251315,
    "warmth": 59.65351922902311,
    "sharpness": 8.524270425091803,
    "boominess": 54.236044999556356,
    "reverb": false
}