{
    "duration": 0.08163265138864517,
    "lossless": 1.0,
    "codec": "pcm_f32le",
    "bitrate": 1411200.0,
    "samplerate": 44100.0,
    "channels": 1.0,
    "audio_md5": "9f341a706a37dbdc85120a15e9e8145f",
    "loudness": -14.875062942504883,
    "dynamic_range": 0.0,
    "temporal_centroid": 0.5963658690452576,
    "log_attack_time": -1.2695070505142212,
    "filesize": 14458,
    "single_event": false,
    "tonality": "D major",
    "tonality_confidence": 0.8641875386238098,
    "loop": false,
    "tempo": 0,
    "tempo_confidence": 0.0,
    "note_midi": 38,
    "note_name": "D2",
    "note_frequency": 73.42839813232422,
    "note_confidence": 0.9578068256378174,
    "hardness": 73.31037069025362,
    "depth": 57.198388768208595,
    "brightness": 55.123364266141074,
    "roughness": 66.69315190295372,
    "warmth": 53.98420214677019,
    "sharpness": 46.762238036010814,
    "boominess": 34.17865146229219,
    "reverb": false
}