{
    "duration": 0.08163265138864517,
    "lossless": 1.0,
    "codec": "pcm_f32le",
    "bitrate": 1411200.0,
    "samplerate": 44100.0,
    "channels": 1.0,
    "audio_md5": "955ac5fdb384be8cba1104f36a940efc",
    "loudness": -9.317965507507324,
    "dynamic_range": 0.0,
    "temporal_centroid": 0.57582688331604,
    "log_attack_time": -1.382699966430664,
    "filesize": 14458,
    "single_event": false,
    "tonality": "E major",
    "tonality_confidence": 0.3989368975162506,
    "loop": false,
    "tempo": 0,
    "tempo_confidence": 0.0,
    "note_midi": 38,
    "note_name": "D2",
    "note_frequency": 73.42861938476562,
    "note_confidence": 0.9575312733650208,
    "hardness": 61.33328993825967,
    "depth": 33.08961598049507,
    "brightness": 62.06714941570524,
    "roughness": 61.84683740339008,
    "warmth": 43.8725096798387,
    "sharpness": 37.529716356533775,
    "boominess": 22.45893075801993,
    "reverb": false
}