{
    "duration": 0.08163265138864517,
    "lossless": 1.0,
    "codec": "pcm_f32le",
    "bitrate": 1411200.0,
    "samplerate": 44100.0,
    "channels": 1.0,
    "audio_md5": "82329665c83ec83cddc1c1f900db9973",
    "loudness": -14.501175880432129,
    "dynamic_range": 0.0,
    "temporal_centroid": 0.5871870517730713,
    "log_attack_time": -1.3339576721191406,
    "filesize": 14458,
    "single_event": false,
    "tonality": "D minor",
    "tonality_confidence": 0.842513382434845,
    "loop": false,
    "tempo": 0,
    "tempo_confidence": 0.0,
    "note_midi": 38,
    "note_name": "D2",
    "note_frequency": 73.4290542602539,
    "note_confidence": 0.9964816570281982,
    "hardness": 39.45433564051616,
    "depth": 59.729785078194766,
    "brightness": 34.47711851514887,
    "roughness": 47.00571242603582,
    "warmth": 56.5898219081434,
    "sharpness": 11.761804043631273,
    "boominess": 44.37200840716103,
    "reverb": false
}