{"duration": 0.08163265138864517, "lossless": 1.0, "codec": "pcm_f32le", "bitrate": 1411200.0, "samplerate": 44100.0, "channels": 1.0, "audio_md5": "3f9b225093fedf4adaea22dbdbdbef12", "loudness": -18.087480545043945, "dynamic_range": 0.0, "temporal_centroid": 0.6301226019859314, "log_attack_time": -1.2559821605682373, "filesize": 14458, "single_event": false, "tonality": "D major", "tonality_confidence": 0.8079019784927368, "loop": false, "tempo": 0, "tempo_confidence": 0.0, "note_midi": 38, "note_name": "D2", "note_frequency": 73.42840576171875, "note_confidence": 0.9985523819923401, "hardness": 69.12395267597702, "depth": 57.52522357671813, "brightness": 54.26712816381563, "roughness": 62.392770111298724, "warmth": 53.25155574809301, "sharpness": 46.39007420650327, "boominess": 33.89391051162316, "reverb": false, "name": "AKWF_1565.wav", "SpectralCentroid": 0.592195274319256, "SpectralSpread": 0.5852905503457381, "SpectralKurtosis": 0.5130190655582281, "ZeroCrossingRate": 0.5688738575398764, "SpectralComplexity": 1.0, "OddToEvenHarmonicEnergyRatio": 0.5694724172243001, "Dissonance": 0.9622718037648039, "PitchSalience": 0.6556411644292192, "HNR": 0.0}