{
    "duration": 0.08163265138864517,
    "lossless": 1.0,
    "codec": "pcm_f32le",
    "bitrate": 1411200.0,
    "samplerate": 44100.0,
    "channels": 1.0,
    "audio_md5": "85530708d3baef195fa8fd29355caa34",
    "loudness": -13.502223014831543,
    "dynamic_range": 0.0,
    "temporal_centroid": 0.5920017957687378,
    "log_attack_time": -1.2847927808761597,
    "filesize": 14458,
    "single_event": false,
    "tonality": "D major",
    "tonality_confidence": 0.807807445526123,
    "loop": false,
    "tempo": 0,
    "tempo_confidence": 0.0,
    "note_midi": 38,
    "note_name": "D2",
    "note_frequency": 73.43045043945312,
    "note_confidence": 0.9565317630767822,
    "hardness": 42.414982407026486,
    "depth": 37.59312029020258,
    "brightness": 40.96914331452629,
    "roughness": 54.1670510988097,
    "warmth": 65.11694052038172,
    "sharpness": 17.350584701527275,
    "boominess": 33.38746093018902,
    "reverb": false
}